django_consent/__init__.py
django_consent/admin.py
django_consent/emails.py
django_consent/forms.py
django_consent/models.py
django_consent/settings.py
django_consent/urls.py
django_consent/utils.py
django_consent/views.py
django_consent/migrations/0001_initial.py
django_consent/migrations/__init__.py
django_consent-0.9b1.dist-info/AUTHORS.rst
django_consent-0.9b1.dist-info/LICENSE
django_consent-0.9b1.dist-info/METADATA
django_consent-0.9b1.dist-info/WHEEL
django_consent-0.9b1.dist-info/top_level.txt
django_consent-0.9b1.dist-info/RECORD
