Metadata-Version: 2.1
Name: django-consent
Version: 0.9b1
Summary: Manages consent for communication with GDPR in mind
Home-page: https://github.com/django-denmark/django_consent
Author: Benjamin Balder Bach
Author-email: benjamin@overtag.dk
License: GNU General Public License v3
Platform: UNKNOWN
Classifier: Environment :: Web Environment
Classifier: Framework :: Django
Classifier: Intended Audience :: Developers
Classifier: License :: OSI Approved :: BSD License
Classifier: Operating System :: OS Independent
Classifier: Programming Language :: Python
Classifier: Programming Language :: Python :: 3
Classifier: Programming Language :: Python :: 3 :: Only
Classifier: Programming Language :: Python :: 3.6
Classifier: Programming Language :: Python :: 3.7
Classifier: Programming Language :: Python :: 3.8
Classifier: Topic :: Internet :: WWW/HTTP
Classifier: Topic :: Internet :: WWW/HTTP :: Dynamic Content
Requires-Python: >=3.6
Requires-Dist: django (<4,>=2.2)
Requires-Dist: django-ratelimit (<4,>=3)
Provides-Extra: develop
Requires-Dist: tox ; extra == 'develop'
Requires-Dist: coverage ; extra == 'develop'
Requires-Dist: pytest ; extra == 'develop'
Requires-Dist: pre-commit ; extra == 'develop'
Provides-Extra: docs
Requires-Dist: sphinx ; extra == 'docs'
Requires-Dist: sphinx-rtd-theme ; extra == 'docs'
Provides-Extra: test
Requires-Dist: pytest ; extra == 'test'
Requires-Dist: pytest-django ; extra == 'test'
Requires-Dist: pytest-cov ; extra == 'test'
Requires-Dist: coverage ; extra == 'test'
Requires-Dist: codecov ; extra == 'test'
